pyonf/__init__.py
pyonf-0.3.dist-info/METADATA
pyonf-0.3.dist-info/WHEEL
pyonf-0.3.dist-info/top_level.txt
pyonf-0.3.dist-info/RECORD
