Metadata-Version: 2.1
Name: pyonf
Version: 0.3
Summary: Easy configuration from command line or YAML file
Home-page: http://github.com/simfu/pyonf
Author: simfu
Author-email: simfu@free.fr
License: GPL
Keywords: configuration option argparse yaml command line argument
Platform: UNKNOWN
Requires-Dist: pyyaml
